{
  "meta": {
    "formatVersion": 1,
    "appVersion": "1.5.0",
    "type": "content-template",
    "name": "Qui"
  },
  "payload": {
    "schema": "template-document-payload-v1",
    "content": {
      "titleText": "Qui",
      "icon": {
        "urls": {
          "URL1": "https://cdn.jsdelivr.net/gh/selfhst/icons@main/svg/qui.svg"
        },
        "linkUrls": {
          "URL1": "https://getqui.com/"
        }
      },
      "hostEntries": [
        {
          "icon": "🔗",
          "label": "Documentation",
          "url": "https://github.com/autobrr/qui"
        }
      ],
      "networkEntries": [
        {
          "icon": "🖥️",
          "value": "Default Port: 7476"
        }
      ],
      "configLocations": [
        {
          "icon": "📁",
          "value": "/root/.config/qui/config.toml"
        }
      ]
    }
  }
}
