{
  "meta": {
    "formatVersion": 1,
    "appVersion": "1.5.0",
    "type": "content-template",
    "name": "Uptime Kuma"
  },
  "payload": {
    "schema": "template-document-payload-v1",
    "content": {
      "titleText": "Uptime Kuma",
      "icon": {
        "urls": {
          "URL1": "https://cdn.jsdelivr.net/gh/selfhst/icons@main/svg/uptime-kuma.svg"
        },
        "linkUrls": {
          "URL1": "https://github.com/louislam/uptime-kuma#uptime-kuma"
        }
      },
      "hostEntries": [
        {
          "icon": "🔗",
          "label": "Documentation",
          "url": "https://github.com/louislam/uptime-kuma/wiki"
        }
      ],
      "networkEntries": [
        {
          "icon": "🖥️",
          "value": "Default Port: 3001"
        }
      ],
      "configLocations": []
    }
  }
}
